llama_index/readers/graphql/__init__.py
llama_index/readers/graphql/base.py
llama_index_readers_graphql-0.4.1.dist-info/METADATA
llama_index_readers_graphql-0.4.1.dist-info/WHEEL
llama_index_readers_graphql-0.4.1.dist-info/licenses/LICENSE
llama_index_readers_graphql-0.4.1.dist-info/RECORD
