Metadata-Version: 2.4
Name: llama-index-readers-graphql
Version: 0.4.1
Summary: llama-index readers graphql integration
Author-email: Your Name <you@example.com>
Maintainer: jexp
License-Expression: MIT
License-File: LICENSE
Keywords: apollo,gql,graphql
Requires-Python: <4.0,>=3.9
Requires-Dist: gql<4,>=3.5.0
Requires-Dist: llama-index-core<0.15,>=0.13.0
Requires-Dist: requests-toolbelt<2,>=1.0.0
